LICENSE
MANIFEST.in
README.md
setup.cfg
setup.py
mobius/__init__.py
mobius/command_line_flags.py
mobius/file_manager.py
mobius/mobius.py
mobius/progress_bar.py
mobius/rawCompare.py
mobius_tunes.egg-info/PKG-INFO
mobius_tunes.egg-info/SOURCES.txt
mobius_tunes.egg-info/dependency_links.txt
mobius_tunes.egg-info/entry_points.txt
mobius_tunes.egg-info/requires.txt
mobius_tunes.egg-info/top_level.txt