Metadata-Version: 1.1
Name: mobius-tunes
Version: 0.1.2
Summary: A program to infinite loop your playlists!
Home-page: https://github.com/MountainRange/mobius-tunes
Author: Jay Kamat
Author-email: github@jgkamat.33mail.com
License: GPLv3
Keywords: infinite jukebox loop songs playlist
Platform: UNKNOWN
Classifier: Development Status :: 3 - Alpha
Classifier: Intended Audience :: End Users/Desktop
Classifier: Topic :: Multimedia :: Sound/Audio :: Mixers
Classifier: License :: OSI Approved :: GNU General Public License v3 (GPLv3)
Classifier: Programming Language :: Python :: 3 :: Only
